{"version":3,"kind":"Article","sha256":"34a817f761324f8b00950d2e160a8a3ead3fefaf5b8d01ce0ac163a774a42335","slug":"getting-started","location":"/guide/getting-started.md","dependencies":[],"frontmatter":{"title":"Getting started","content_includes_title":false,"authors":[{"nameParsed":{"literal":"Andrew Hutchings","given":"Andrew","family":"Hutchings"},"name":"Andrew Hutchings","id":"contributors-myst-generated-uid-0"}],"github":"https://github.com/LinuxJedi/Copperline","keywords":["amiga","emulator","ocs","ecs","rust"],"numbering":{"title":{"offset":1}},"source_url":"https://github.com/LinuxJedi/Copperline/blob/main/docs/guide/getting-started.md","edit_url":"https://github.com/LinuxJedi/Copperline/edit/main/docs/guide/getting-started.md","thumbnail":"/docs/build/kick13-insert-disk-afeec8ff541e81973d66bd88167c35f9.png","exports":[{"format":"md","filename":"getting-started.md","url":"/docs/build/getting-started-a1384fdf514ac3a0c31e56d5eac6f3a3.md"}]},"mdast":{"type":"root","children":[{"type":"block","children":[{"type":"paragraph","position":{"start":{"line":3,"column":1},"end":{"line":6,"column":1}},"children":[{"type":"text","value":"To try Copperline without installing anything, a WebAssembly build runs\nin the browser at ","position":{"start":{"line":3,"column":1},"end":{"line":3,"column":1}},"key":"vCDyjOx8pR"},{"type":"link","url":"https://copperline.dev/try/","position":{"start":{"line":3,"column":1},"end":{"line":3,"column":1}},"children":[{"type":"text","value":"copperline.dev/try","position":{"start":{"line":3,"column":1},"end":{"line":3,"column":1}},"key":"XvbJtTKkP3"}],"urlSource":"https://copperline.dev/try/","key":"jhahq4W0MB"},{"type":"text","value":"; see\n","position":{"start":{"line":3,"column":1},"end":{"line":3,"column":1}},"key":"fModl3bIxf"},{"type":"link","url":"/browser","position":{"start":{"line":3,"column":1},"end":{"line":3,"column":1}},"children":[{"type":"text","value":"The browser build","key":"RBvuVn3Ew4"}],"urlSource":"browser","dataUrl":"/browser.json","internal":true,"protocol":"file","key":"Vf0ojOCzvL"},{"type":"text","value":" for what it can do. The rest of this chapter covers the\nnative desktop build.","position":{"start":{"line":3,"column":1},"end":{"line":3,"column":1}},"key":"rSksjzxiLP"}],"key":"eLV2yDwR2i"},{"type":"heading","depth":2,"position":{"start":{"line":8,"column":1},"end":{"line":8,"column":1}},"children":[{"type":"text","value":"Requirements","position":{"start":{"line":8,"column":1},"end":{"line":8,"column":1}},"key":"DHyTefkrRD"}],"identifier":"requirements","label":"Requirements","html_id":"requirements","implicit":true,"key":"xOTcPVulk1"},{"type":"list","ordered":false,"spread":false,"position":{"start":{"line":10,"column":1},"end":{"line":24,"column":1}},"children":[{"type":"listItem","spread":true,"position":{"start":{"line":10,"column":1},"end":{"line":10,"column":1}},"children":[{"type":"paragraph","children":[{"type":"text","value":"Rust 1.87+ (stable). Tested with Rust 1.96.","position":{"start":{"line":10,"column":1},"end":{"line":10,"column":1}},"key":"wsAzBHjl7c"}],"key":"SnEF1KmAWg"}],"key":"frQWfBsQOV"},{"type":"listItem","spread":true,"position":{"start":{"line":11,"column":1},"end":{"line":13,"column":1}},"children":[{"type":"paragraph","children":[{"type":"text","value":"macOS, Linux, or Windows. There is no SDL2 dependency: video uses\n","position":{"start":{"line":11,"column":1},"end":{"line":11,"column":1}},"key":"BazhMCZBWT"},{"type":"inlineCode","value":"winit","position":{"start":{"line":11,"column":1},"end":{"line":11,"column":1}},"key":"kjTq2GGzdf"},{"type":"text","value":" + ","position":{"start":{"line":11,"column":1},"end":{"line":11,"column":1}},"key":"CbUNbITWmx"},{"type":"inlineCode","value":"pixels","position":{"start":{"line":11,"column":1},"end":{"line":11,"column":1}},"key":"zu9cVqhJFW"},{"type":"text","value":", audio uses ","position":{"start":{"line":11,"column":1},"end":{"line":11,"column":1}},"key":"rkJzDpbCec"},{"type":"inlineCode","value":"cpal","position":{"start":{"line":11,"column":1},"end":{"line":11,"column":1}},"key":"A2FkCYQ2R8"},{"type":"text","value":", and gamepads use the pure-Rust\n","position":{"start":{"line":11,"column":1},"end":{"line":11,"column":1}},"key":"Yk0ovYPREy"},{"type":"inlineCode","value":"gilrs","position":{"start":{"line":11,"column":1},"end":{"line":11,"column":1}},"key":"hvPUyifIVt"},{"type":"text","value":" crate.","position":{"start":{"line":11,"column":1},"end":{"line":11,"column":1}},"key":"FqAxr0oUXf"}],"key":"SP5bCDImQl"}],"key":"iGwjcHv6aA"},{"type":"listItem","spread":true,"position":{"start":{"line":14,"column":1},"end":{"line":15,"column":1}},"children":[{"type":"paragraph","children":[{"type":"text","value":"A GPU backend for presentation: Metal on macOS, DX12 on Windows, and\n","position":{"start":{"line":14,"column":1},"end":{"line":14,"column":1}},"key":"dd84M1SrHy"},{"type":"strong","position":{"start":{"line":14,"column":1},"end":{"line":14,"column":1}},"children":[{"type":"text","value":"Vulkan on Linux","position":{"start":{"line":14,"column":1},"end":{"line":14,"column":1}},"key":"qNXfdpfSjB"}],"key":"RzBTgho9mL"},{"type":"text","value":" (see ","position":{"start":{"line":14,"column":1},"end":{"line":14,"column":1}},"key":"yEny7w6XQ6"},{"type":"crossReference","position":{"start":{"line":14,"column":1},"end":{"line":14,"column":1}},"children":[{"type":"text","value":"Vulkan is required on Linux","position":{"start":{"line":73,"column":1},"end":{"line":73,"column":1}},"key":"wGwNr9NAAV"}],"identifier":"vulkan-is-required-on-linux","label":"vulkan-is-required-on-linux","kind":"heading","template":"{name}","resolved":true,"html_id":"vulkan-is-required-on-linux","key":"pwNnn7Yi95"},{"type":"text","value":").","position":{"start":{"line":14,"column":1},"end":{"line":14,"column":1}},"key":"iKKnQ4wRjc"}],"key":"pBDIiLZ5Ev"}],"key":"ziXTZ5T5QI"},{"type":"listItem","spread":true,"position":{"start":{"line":16,"column":1},"end":{"line":16,"column":1}},"children":[{"type":"paragraph","children":[{"type":"text","value":"Fedora build dependencies: ","position":{"start":{"line":16,"column":1},"end":{"line":16,"column":1}},"key":"HL9oFpsBtZ"},{"type":"inlineCode","value":"sudo dnf install alsa-lib-devel systemd-devel","position":{"start":{"line":16,"column":1},"end":{"line":16,"column":1}},"key":"jugS04TAp1"},{"type":"text","value":".","position":{"start":{"line":16,"column":1},"end":{"line":16,"column":1}},"key":"r2UWbU2cSq"}],"key":"Mben2IvcZZ"}],"key":"JA6jsYWwwE"},{"type":"listItem","spread":true,"position":{"start":{"line":17,"column":1},"end":{"line":24,"column":1}},"children":[{"type":"paragraph","children":[{"type":"text","value":"A boot ROM. Copperline ships with the ","position":{"start":{"line":17,"column":1},"end":{"line":17,"column":1}},"key":"EdUAar7CF2"},{"type":"link","url":"http://www.aros.org/","position":{"start":{"line":17,"column":1},"end":{"line":17,"column":1}},"children":[{"type":"text","value":"AROS","position":{"start":{"line":17,"column":1},"end":{"line":17,"column":1}},"key":"P4Hkn3dp4d"}],"urlSource":"http://www.aros.org/","key":"XUpTBda6f8"},{"type":"text","value":"\nopen-source Kickstart replacement and boots it by default, so it runs out\nof the box with no ROM of your own. It also boots Kickstart 1.3, 2.05, and\n3.1 (including the CDTV and CD32 extended ROMs) as well as\n","position":{"start":{"line":17,"column":1},"end":{"line":17,"column":1}},"key":"lllqIAK37c"},{"type":"link","url":"https://www.diagrom.com/","position":{"start":{"line":17,"column":1},"end":{"line":17,"column":1}},"children":[{"type":"text","value":"DiagROM","position":{"start":{"line":17,"column":1},"end":{"line":17,"column":1}},"key":"nvEQO80aNB"}],"urlSource":"https://www.diagrom.com/","key":"UAzqissjkU"},{"type":"text","value":". Main Kickstart images must be exactly\n512 KiB; CDTV/CD32 extended ROM sizes are covered in\n","position":{"start":{"line":17,"column":1},"end":{"line":17,"column":1}},"key":"kFLMOk1SaX"},{"type":"crossReference","url":"/configuration","position":{"start":{"line":17,"column":1},"end":{"line":17,"column":1}},"children":[{"type":"text","value":"Top level","position":{"start":{"line":69,"column":1},"end":{"line":69,"column":1}},"key":"Y1QZ8h76r7"}],"urlSource":"configuration#top-level","dataUrl":"/configuration.json","identifier":"top-level","label":"top-level","remote":true,"protocol":"file","kind":"heading","template":"{name}","resolved":true,"html_id":"top-level","key":"lUl2NZDp4M"},{"type":"text","value":".","position":{"start":{"line":17,"column":1},"end":{"line":17,"column":1}},"key":"YUyHa64YoN"}],"key":"ax37XtmM5g"}],"key":"kRkg2FVX1l"}],"key":"oNZ6TRlaXz"},{"type":"heading","depth":2,"position":{"start":{"line":25,"column":1},"end":{"line":25,"column":1}},"children":[{"type":"text","value":"Installing on macOS (Homebrew)","position":{"start":{"line":25,"column":1},"end":{"line":25,"column":1}},"key":"QlFHzEWmgQ"}],"identifier":"installing-on-macos-homebrew","label":"Installing on macOS (Homebrew)","html_id":"installing-on-macos-homebrew","implicit":true,"key":"c9VhERUxOc"},{"type":"code","lang":"sh","value":"brew tap LinuxJedi/copperline https://github.com/LinuxJedi/Copperline\nbrew install copperline","position":{"start":{"line":27,"column":1},"end":{"line":30,"column":1}},"key":"yUY9hbBewn"},{"type":"paragraph","position":{"start":{"line":32,"column":1},"end":{"line":36,"column":1}},"children":[{"type":"text","value":"The formula builds from source, so the binary is compiled locally and is not\nsubject to macOS Gatekeeper quarantine: there is no Security & Privacy\noverride to click through, unlike a downloaded prebuilt app. Use\n","position":{"start":{"line":32,"column":1},"end":{"line":32,"column":1}},"key":"k3KhKL5cD4"},{"type":"inlineCode","value":"brew install --HEAD copperline","position":{"start":{"line":32,"column":1},"end":{"line":32,"column":1}},"key":"kxB4XImHgh"},{"type":"text","value":" to build the latest ","position":{"start":{"line":32,"column":1},"end":{"line":32,"column":1}},"key":"iincQndt9k"},{"type":"inlineCode","value":"main","position":{"start":{"line":32,"column":1},"end":{"line":32,"column":1}},"key":"jYorzA9viR"},{"type":"text","value":" instead of the\nmost recent tagged release, then run ","position":{"start":{"line":32,"column":1},"end":{"line":32,"column":1}},"key":"tCRrOs0QH5"},{"type":"inlineCode","value":"copperline","position":{"start":{"line":32,"column":1},"end":{"line":32,"column":1}},"key":"WXrvmMm4jG"},{"type":"text","value":" from the terminal.","position":{"start":{"line":32,"column":1},"end":{"line":32,"column":1}},"key":"vJwqMGifEZ"}],"key":"TtaMuT4DLF"},{"type":"paragraph","position":{"start":{"line":38,"column":1},"end":{"line":46,"column":1}},"children":[{"type":"text","value":"For a no-compiler install, download ","position":{"start":{"line":38,"column":1},"end":{"line":38,"column":1}},"key":"RrFmnljq7G"},{"type":"inlineCode","value":"Copperline-X.Y.Z-macos-universal.dmg","position":{"start":{"line":38,"column":1},"end":{"line":38,"column":1}},"key":"WeoiHW0dyy"},{"type":"text","value":"\nfrom the ","position":{"start":{"line":38,"column":1},"end":{"line":38,"column":1}},"key":"PZSkPvCRFW"},{"type":"link","url":"https://github.com/LinuxJedi/Copperline/releases","position":{"start":{"line":38,"column":1},"end":{"line":38,"column":1}},"children":[{"type":"text","value":"releases page","position":{"start":{"line":38,"column":1},"end":{"line":38,"column":1}},"key":"JHdALfRWbI"}],"urlSource":"https://github.com/LinuxJedi/Copperline/releases","error":true,"key":"YYTF5UvJzn"},{"type":"text","value":",\nopen it, and drag ","position":{"start":{"line":38,"column":1},"end":{"line":38,"column":1}},"key":"qqntaptXO8"},{"type":"inlineCode","value":"Copperline.app","position":{"start":{"line":38,"column":1},"end":{"line":38,"column":1}},"key":"a6npJPEQ84"},{"type":"text","value":" onto the Applications shortcut. The app is a\nuniversal binary that runs natively on Apple Silicon and Intel, and bundles the\nAROS boot ROM, so it runs out of the box. The image is not code-signed or\nnotarized, so on first launch Gatekeeper refuses to open it; right-click (or\nControl-click) the app and choose ","position":{"start":{"line":38,"column":1},"end":{"line":38,"column":1}},"key":"TftaWA80gu"},{"type":"strong","position":{"start":{"line":38,"column":1},"end":{"line":38,"column":1}},"children":[{"type":"text","value":"Open","position":{"start":{"line":38,"column":1},"end":{"line":38,"column":1}},"key":"j850kbUQ3e"}],"key":"tFyAJNUkWz"},{"type":"text","value":", then confirm. macOS remembers the\nchoice. If it still refuses, clear the download quarantine with\n","position":{"start":{"line":38,"column":1},"end":{"line":38,"column":1}},"key":"nATHM1OdZs"},{"type":"inlineCode","value":"xattr -dr com.apple.quarantine /Applications/Copperline.app","position":{"start":{"line":38,"column":1},"end":{"line":38,"column":1}},"key":"fTsuwanMi8"},{"type":"text","value":".","position":{"start":{"line":38,"column":1},"end":{"line":38,"column":1}},"key":"hJg3xaIHfe"}],"key":"KUEY43HY0Q"},{"type":"heading","depth":2,"position":{"start":{"line":48,"column":1},"end":{"line":48,"column":1}},"children":[{"type":"text","value":"Installing on Linux","position":{"start":{"line":48,"column":1},"end":{"line":48,"column":1}},"key":"LCIFmU9wqW"}],"identifier":"installing-on-linux","label":"Installing on Linux","html_id":"installing-on-linux","implicit":true,"key":"SNNKM4J34y"},{"type":"paragraph","position":{"start":{"line":50,"column":1},"end":{"line":50,"column":1}},"children":[{"type":"text","value":"Two channels are provided.","position":{"start":{"line":50,"column":1},"end":{"line":50,"column":1}},"key":"dFSDcG5TwS"}],"key":"IqPU3hX3Hl"},{"type":"paragraph","position":{"start":{"line":52,"column":1},"end":{"line":54,"column":1}},"children":[{"type":"strong","position":{"start":{"line":52,"column":1},"end":{"line":52,"column":1}},"children":[{"type":"text","value":"Flatpak","position":{"start":{"line":52,"column":1},"end":{"line":52,"column":1}},"key":"S7iO8Ere05"}],"key":"SUdPhbSGI7"},{"type":"text","value":" (recommended) works on any distribution and pulls in the GPU,\naudio and portal stack from the Freedesktop runtime, so there is nothing else\nto install:","position":{"start":{"line":52,"column":1},"end":{"line":52,"column":1}},"key":"Ef6iYfcueD"}],"key":"Tbx0FPV3l1"},{"type":"code","lang":"sh","value":"flatpak install flathub dev.copperline.Copperline\nflatpak run dev.copperline.Copperline","position":{"start":{"line":56,"column":1},"end":{"line":59,"column":1}},"key":"jkPZvQlQlQ"},{"type":"paragraph","position":{"start":{"line":61,"column":1},"end":{"line":63,"column":1}},"children":[{"type":"strong","position":{"start":{"line":61,"column":1},"end":{"line":61,"column":1}},"children":[{"type":"text","value":"AppImage","position":{"start":{"line":61,"column":1},"end":{"line":61,"column":1}},"key":"X09I1u6Ib6"}],"key":"XB1XGn3AZE"},{"type":"text","value":" is a single self-contained file that needs no installation:\ndownload ","position":{"start":{"line":61,"column":1},"end":{"line":61,"column":1}},"key":"OMmtWbE7Zi"},{"type":"inlineCode","value":"Copperline-X.Y.Z-<arch>.AppImage","position":{"start":{"line":61,"column":1},"end":{"line":61,"column":1}},"key":"wuUBVv9XSc"},{"type":"text","value":" from the\n","position":{"start":{"line":61,"column":1},"end":{"line":61,"column":1}},"key":"ghrnYobwJ9"},{"type":"link","url":"https://github.com/LinuxJedi/Copperline/releases","position":{"start":{"line":61,"column":1},"end":{"line":61,"column":1}},"children":[{"type":"text","value":"releases page","position":{"start":{"line":61,"column":1},"end":{"line":61,"column":1}},"key":"yyMt7ke61w"}],"urlSource":"https://github.com/LinuxJedi/Copperline/releases","error":true,"key":"xSu7anOo6N"},{"type":"text","value":", then:","position":{"start":{"line":61,"column":1},"end":{"line":61,"column":1}},"key":"GL11Ozz1Zh"}],"key":"pzrgxQevmy"},{"type":"code","lang":"sh","value":"chmod +x Copperline-*.AppImage\n./Copperline-*.AppImage","position":{"start":{"line":65,"column":1},"end":{"line":68,"column":1}},"key":"D0lGF53iBX"},{"type":"paragraph","position":{"start":{"line":70,"column":1},"end":{"line":71,"column":1}},"children":[{"type":"text","value":"Both bundle the AROS boot ROM, so they run out of the box. Packaging sources\nlive in ","position":{"start":{"line":70,"column":1},"end":{"line":70,"column":1}},"key":"NNUgYmvxI4"},{"type":"inlineCode","value":"packaging/flatpak/","position":{"start":{"line":70,"column":1},"end":{"line":70,"column":1}},"key":"rQBdUBFkWT"},{"type":"text","value":" and ","position":{"start":{"line":70,"column":1},"end":{"line":70,"column":1}},"key":"Zdg9ZgarQV"},{"type":"inlineCode","value":"packaging/appimage/","position":{"start":{"line":70,"column":1},"end":{"line":70,"column":1}},"key":"I4HtRHbb6k"},{"type":"text","value":".","position":{"start":{"line":70,"column":1},"end":{"line":70,"column":1}},"key":"KESj6UjCsB"}],"key":"RCZ87hxoIb"},{"type":"heading","depth":3,"position":{"start":{"line":73,"column":1},"end":{"line":73,"column":1}},"children":[{"type":"text","value":"Vulkan is required on Linux","position":{"start":{"line":73,"column":1},"end":{"line":73,"column":1}},"key":"FTgunT4XUc"}],"identifier":"vulkan-is-required-on-linux","label":"Vulkan is required on Linux","html_id":"vulkan-is-required-on-linux","implicit":true,"key":"qvX5ByZTGy"},{"type":"paragraph","position":{"start":{"line":75,"column":1},"end":{"line":79,"column":1}},"children":[{"type":"text","value":"The display is presented through wgpu’s Vulkan backend. The OpenGL fallback\nis disabled because wgpu initializes its EGL instance without a display\nhandle and silently selects Mesa’s “surfaceless” platform, which cannot be\npaired with an on-screen window; adapter selection then fails. The symptom is\nthe window flashing open and immediately exiting with:","position":{"start":{"line":75,"column":1},"end":{"line":75,"column":1}},"key":"foqscxbUuH"}],"key":"JMUBg1dMVy"},{"type":"code","lang":"","value":"ERROR copperline::video::window] pixels init failed: No suitable `wgpu::Adapter` found.","position":{"start":{"line":81,"column":1},"end":{"line":83,"column":1}},"key":"RjGvNpyq65"},{"type":"paragraph","position":{"start":{"line":85,"column":1},"end":{"line":87,"column":1}},"children":[{"type":"text","value":"The fix is to provide a Vulkan driver. Any GPU from roughly Intel Skylake /\n2015 onward ships a hardware Vulkan driver in ","position":{"start":{"line":85,"column":1},"end":{"line":85,"column":1}},"key":"zQwxPcSzbc"},{"type":"inlineCode","value":"mesa","position":{"start":{"line":85,"column":1},"end":{"line":85,"column":1}},"key":"frVZqqbNBa"},{"type":"text","value":". Older hardware, a\nheadless host, or a VM can use the software lavapipe ICD instead:","position":{"start":{"line":85,"column":1},"end":{"line":85,"column":1}},"key":"SQlGQ2Mep6"}],"key":"yRg2kjAiFq"},{"type":"list","ordered":false,"spread":false,"position":{"start":{"line":89,"column":1},"end":{"line":92,"column":1}},"children":[{"type":"listItem","spread":true,"position":{"start":{"line":89,"column":1},"end":{"line":89,"column":1}},"children":[{"type":"paragraph","children":[{"type":"text","value":"Arch: ","position":{"start":{"line":89,"column":1},"end":{"line":89,"column":1}},"key":"i6CezYV9Q3"},{"type":"inlineCode","value":"sudo pacman -S vulkan-swrast","position":{"start":{"line":89,"column":1},"end":{"line":89,"column":1}},"key":"wr4MR9FMwI"}],"key":"BgRcHdTJfN"}],"key":"A6YB23YJnx"},{"type":"listItem","spread":true,"position":{"start":{"line":90,"column":1},"end":{"line":90,"column":1}},"children":[{"type":"paragraph","children":[{"type":"text","value":"Debian/Ubuntu: ","position":{"start":{"line":90,"column":1},"end":{"line":90,"column":1}},"key":"kjlASpAV9E"},{"type":"inlineCode","value":"sudo apt install mesa-vulkan-drivers","position":{"start":{"line":90,"column":1},"end":{"line":90,"column":1}},"key":"b0hyo9r6yF"}],"key":"kBZiofi95b"}],"key":"DwaLXvEDlj"},{"type":"listItem","spread":true,"position":{"start":{"line":91,"column":1},"end":{"line":92,"column":1}},"children":[{"type":"paragraph","children":[{"type":"text","value":"Fedora: ","position":{"start":{"line":91,"column":1},"end":{"line":91,"column":1}},"key":"xlSmpngMmU"},{"type":"inlineCode","value":"sudo dnf install mesa-vulkan-drivers","position":{"start":{"line":91,"column":1},"end":{"line":91,"column":1}},"key":"eeAZVyFbAD"}],"key":"EOfIx7d5MS"}],"key":"Eq1GuRb3LO"}],"key":"qbLvvCA5up"},{"type":"paragraph","position":{"start":{"line":93,"column":1},"end":{"line":97,"column":1}},"children":[{"type":"text","value":"Copperline renders entirely on the CPU and only asks the GPU to blit one\nframebuffer per frame, so software Vulkan is perfectly adequate. The Flatpak\nruntime already includes lavapipe, so the Flatpak needs no extra package.\n","position":{"start":{"line":93,"column":1},"end":{"line":93,"column":1}},"key":"MYd5VF3D3O"},{"type":"inlineCode","value":"WGPU_BACKEND","position":{"start":{"line":93,"column":1},"end":{"line":93,"column":1}},"key":"huuTOkNqpX"},{"type":"text","value":" overrides backend selection if you need to force one for\ndebugging.","position":{"start":{"line":93,"column":1},"end":{"line":93,"column":1}},"key":"x32SIblLNM"}],"key":"vY6WtJcEbg"},{"type":"heading","depth":2,"position":{"start":{"line":99,"column":1},"end":{"line":99,"column":1}},"children":[{"type":"text","value":"Building","position":{"start":{"line":99,"column":1},"end":{"line":99,"column":1}},"key":"S3ISJRDKdr"}],"identifier":"building","label":"Building","html_id":"building","implicit":true,"key":"f8RxnCLkJ0"},{"type":"code","lang":"sh","value":"cargo build --release","position":{"start":{"line":101,"column":1},"end":{"line":103,"column":1}},"key":"OTkIyn4irv"},{"type":"admonition","kind":"warning","children":[{"type":"admonitionTitle","children":[{"type":"text","value":"Warning","key":"NmQfc3H11i"}],"key":"JlcQNL98FQ"},{"type":"paragraph","position":{"start":{"line":106,"column":1},"end":{"line":107,"column":1}},"children":[{"type":"text","value":"Always use a release build to run software. Debug builds are far too slow\nfor real-time emulation.","position":{"start":{"line":106,"column":1},"end":{"line":106,"column":1}},"key":"oGNBvQUgRW"}],"key":"z7uw48iOIa"}],"key":"Q3SfuCNWxY"},{"type":"paragraph","position":{"start":{"line":110,"column":1},"end":{"line":110,"column":1}},"children":[{"type":"text","value":"The test suite needs no external assets:","position":{"start":{"line":110,"column":1},"end":{"line":110,"column":1}},"key":"JAfLAaY0GV"}],"key":"lLzDCDvcRD"},{"type":"code","lang":"sh","value":"cargo test                          # asset-free test suite\ncargo test --release -- --ignored   # integration tests (need local ROMs/disks)","position":{"start":{"line":112,"column":1},"end":{"line":115,"column":1}},"key":"Dk1HkJKenl"},{"type":"heading","depth":2,"position":{"start":{"line":117,"column":1},"end":{"line":117,"column":1}},"children":[{"type":"text","value":"First boot","position":{"start":{"line":117,"column":1},"end":{"line":117,"column":1}},"key":"nUSx4pj0pY"}],"identifier":"first-boot","label":"First boot","html_id":"first-boot","implicit":true,"key":"uuCOnU7CdG"},{"type":"code","lang":"sh","value":"./target/release/copperline","position":{"start":{"line":119,"column":1},"end":{"line":121,"column":1}},"key":"Vcu1unHVGV"},{"type":"paragraph","position":{"start":{"line":123,"column":1},"end":{"line":132,"column":1}},"children":[{"type":"text","value":"With no arguments and no ","position":{"start":{"line":123,"column":1},"end":{"line":123,"column":1}},"key":"AIEPxIdjRd"},{"type":"inlineCode","value":"./copperline.toml","position":{"start":{"line":123,"column":1},"end":{"line":123,"column":1}},"key":"cAZ6gJFmo9"},{"type":"text","value":" in the current directory,\nCopperline opens the ","position":{"start":{"line":123,"column":1},"end":{"line":123,"column":1}},"key":"Xoo2jSnKRi"},{"type":"strong","position":{"start":{"line":123,"column":1},"end":{"line":123,"column":1}},"children":[{"type":"text","value":"configuration screen","position":{"start":{"line":123,"column":1},"end":{"line":123,"column":1}},"key":"YG6313NKx0"}],"key":"UlSX6eMtfI"},{"type":"text","value":" -- a launcher that lets you pick\na machine, configure everything about it, load and save ","position":{"start":{"line":123,"column":1},"end":{"line":123,"column":1}},"key":"P1qtA7jqq5"},{"type":"inlineCode","value":".toml","position":{"start":{"line":123,"column":1},"end":{"line":123,"column":1}},"key":"wgEKrHCERv"},{"type":"text","value":" configs, and\npress ","position":{"start":{"line":123,"column":1},"end":{"line":123,"column":1}},"key":"xWzWxS2cfG"},{"type":"strong","position":{"start":{"line":123,"column":1},"end":{"line":123,"column":1}},"children":[{"type":"text","value":"Run","position":{"start":{"line":123,"column":1},"end":{"line":123,"column":1}},"key":"u6J7tIrwY7"}],"key":"FtECLnDs50"},{"type":"text","value":" to boot. See ","position":{"start":{"line":123,"column":1},"end":{"line":123,"column":1}},"key":"OC9RGlpeuQ"},{"type":"crossReference","url":"/ui","position":{"start":{"line":123,"column":1},"end":{"line":123,"column":1}},"children":[{"type":"text","value":"Machine configuration screen","position":{"start":{"line":190,"column":1},"end":{"line":190,"column":1}},"key":"gRrZcNCsVs"}],"urlSource":"ui#machine-configuration-screen","dataUrl":"/ui.json","identifier":"machine-configuration-screen","label":"machine-configuration-screen","remote":true,"protocol":"file","kind":"heading","template":"{name}","resolved":true,"html_id":"machine-configuration-screen","key":"vvccDsdz7t"},{"type":"text","value":" for a full tour.\nThe screen starts from the built-in defaults: the A500 Rev 6A -- the most\ncommon and most-targeted Amiga: a 68000 at ~7.09 MHz, the ECS “Fatter” 8372A\nAgnus (1 MiB chip reach plus the software PAL/NTSC switch) with the original\nOCS 8362 Denise, 512 KiB chip RAM plus 512 KiB of trapdoor slow RAM, PAL, and\nthe bundled AROS ROM (when no ROM is named, Copperline locates the AROS image\nthat ships with it -- see ","position":{"start":{"line":123,"column":1},"end":{"line":123,"column":1}},"key":"nPP5fyrcwi"},{"type":"crossReference","url":"/configuration","position":{"start":{"line":123,"column":1},"end":{"line":123,"column":1}},"children":[{"type":"text","value":"Top level","position":{"start":{"line":69,"column":1},"end":{"line":69,"column":1}},"key":"cDUsc0xLyD"}],"urlSource":"configuration#top-level","dataUrl":"/configuration.json","identifier":"top-level","label":"top-level","remote":true,"protocol":"file","kind":"heading","template":"{name}","resolved":true,"html_id":"top-level","key":"VBTxQzf2GU"},{"type":"text","value":").","position":{"start":{"line":123,"column":1},"end":{"line":123,"column":1}},"key":"LkV2rFrCgr"}],"key":"zzXp5BMkwI"},{"type":"paragraph","position":{"start":{"line":134,"column":1},"end":{"line":138,"column":1}},"children":[{"type":"text","value":"Copperline boots directly, skipping the configuration screen, whenever a\nmachine is specified: a ","position":{"start":{"line":134,"column":1},"end":{"line":134,"column":1}},"key":"v8CVRlNPSX"},{"type":"inlineCode","value":"./copperline.toml","position":{"start":{"line":134,"column":1},"end":{"line":134,"column":1}},"key":"Op9vM97J2E"},{"type":"text","value":" in the current directory, an\nexplicit ","position":{"start":{"line":134,"column":1},"end":{"line":134,"column":1}},"key":"pr3gYo3Rah"},{"type":"inlineCode","value":"--config","position":{"start":{"line":134,"column":1},"end":{"line":134,"column":1}},"key":"hPlTl90yf4"},{"type":"text","value":" file, a ROM or override on the command line, or any\nheadless/scripted run. You can reopen the configuration screen at any time from\nthe menu (see ","position":{"start":{"line":134,"column":1},"end":{"line":134,"column":1}},"key":"T6oQdQZbxn"},{"type":"crossReference","url":"/ui","position":{"start":{"line":134,"column":1},"end":{"line":134,"column":1}},"children":[{"type":"text","value":"Machine configuration screen","position":{"start":{"line":190,"column":1},"end":{"line":190,"column":1}},"key":"hrf7JgBN6N"}],"urlSource":"ui#machine-configuration-screen","dataUrl":"/ui.json","identifier":"machine-configuration-screen","label":"machine-configuration-screen","remote":true,"protocol":"file","kind":"heading","template":"{name}","resolved":true,"html_id":"machine-configuration-screen","key":"dnnLioNT4n"},{"type":"text","value":").","position":{"start":{"line":134,"column":1},"end":{"line":134,"column":1}},"key":"K3Njcz6EPq"}],"key":"BbTeKxgmYO"},{"type":"paragraph","position":{"start":{"line":140,"column":1},"end":{"line":141,"column":1}},"children":[{"type":"text","value":"You can boot your own ROM with a positional argument, or point at a specific\nconfig file:","position":{"start":{"line":140,"column":1},"end":{"line":140,"column":1}},"key":"U6tc8INjTa"}],"key":"EyLX63BYzv"},{"type":"code","lang":"sh","value":"./target/release/copperline path/to/kickstart.rom\n./target/release/copperline --config path/to/copperline.toml","position":{"start":{"line":143,"column":1},"end":{"line":146,"column":1}},"key":"dR7kqnO9Ml"},{"type":"paragraph","position":{"start":{"line":148,"column":1},"end":{"line":150,"column":1}},"children":[{"type":"text","value":"The common machine knobs can also be set straight on the command line,\nwithout writing a config file at all -- the machine model, chipset, CPU\n(and its clock/FPU), and the chip/fast/slow RAM sizes:","position":{"start":{"line":148,"column":1},"end":{"line":148,"column":1}},"key":"n9pa1WerAi"}],"key":"TQmrceukH1"},{"type":"code","lang":"sh","value":"./target/release/copperline --model A1200 --fast 8M KICK31.ROM","position":{"start":{"line":152,"column":1},"end":{"line":154,"column":1}},"key":"Adn9p1bqaa"},{"type":"paragraph","position":{"start":{"line":156,"column":1},"end":{"line":158,"column":1}},"children":[{"type":"text","value":"See ","position":{"start":{"line":156,"column":1},"end":{"line":156,"column":1}},"key":"rT7Ea3Fut9"},{"type":"crossReference","url":"/configuration","position":{"start":{"line":156,"column":1},"end":{"line":156,"column":1}},"children":[{"type":"text","value":"Command-line overrides","position":{"start":{"line":29,"column":1},"end":{"line":29,"column":1}},"key":"gGuKq1gm0i"}],"urlSource":"configuration#command-line-overrides","dataUrl":"/configuration.json","identifier":"command-line-overrides","label":"command-line-overrides","remote":true,"protocol":"file","kind":"heading","template":"{name}","resolved":true,"html_id":"command-line-overrides","key":"pFl7FeuhYd"},{"type":"text","value":" for the full list.\n","position":{"start":{"line":156,"column":1},"end":{"line":156,"column":1}},"key":"FU6iwWeglf"},{"type":"inlineCode","value":"copperline --help","position":{"start":{"line":156,"column":1},"end":{"line":156,"column":1}},"key":"Oj2G6GKvcy"},{"type":"text","value":" lists every flag, and ","position":{"start":{"line":156,"column":1},"end":{"line":156,"column":1}},"key":"NMM9jnBjGh"},{"type":"inlineCode","value":"copperline --version","position":{"start":{"line":156,"column":1},"end":{"line":156,"column":1}},"key":"aQ7f11IS8P"},{"type":"text","value":" prints\nthe release version.","position":{"start":{"line":156,"column":1},"end":{"line":156,"column":1}},"key":"Ku3H6Nbzd0"}],"key":"wd81NlM5zf"},{"type":"paragraph","position":{"start":{"line":160,"column":1},"end":{"line":161,"column":1}},"children":[{"type":"text","value":"A Kickstart 1.3 machine with no disk boots to the familiar insert-disk\nscreen:","position":{"start":{"line":160,"column":1},"end":{"line":160,"column":1}},"key":"y9V2J0H1Fl"}],"key":"asnqHQP41W"},{"type":"container","kind":"figure","children":[{"type":"image","url":"/docs/build/kick13-insert-disk-afeec8ff541e81973d66bd88167c35f9.png","alt":"Kickstart 1.3 insert-disk screen","width":"75%","key":"JlxaYbT5XH","urlSource":"../images/kick13-insert-disk.png"},{"type":"caption","children":[{"type":"paragraph","position":{"start":{"line":167,"column":1},"end":{"line":167,"column":1}},"children":[{"type":"text","value":"Kickstart 1.3 waiting for a boot floppy.","position":{"start":{"line":167,"column":1},"end":{"line":167,"column":1}},"key":"VLc8G5WZBe"}],"key":"ngRxuzU5cp"}],"key":"nn1Mnt3Slx"}],"enumerator":"1","key":"bmuJHcdxqQ"},{"type":"paragraph","position":{"start":{"line":170,"column":1},"end":{"line":170,"column":1}},"children":[{"type":"text","value":"To boot a disk, add a floppy section to your config:","position":{"start":{"line":170,"column":1},"end":{"line":170,"column":1}},"key":"SlBa2baeNe"}],"key":"yb6DMHHfXT"},{"type":"code","lang":"toml","value":"rom = \"KICK13.ROM\"\n\n[floppy.df0]\npath = \"MyGame.adf\"","position":{"start":{"line":172,"column":1},"end":{"line":177,"column":1}},"key":"zZRccoez0W"},{"type":"paragraph","position":{"start":{"line":179,"column":1},"end":{"line":180,"column":1}},"children":[{"type":"text","value":"Copperline accepts plain ADF images, gzip-compressed images, single file ZIP\narchives, DMS archives, UAE extended ADFs, and read-only SCP flux images.","position":{"start":{"line":179,"column":1},"end":{"line":179,"column":1}},"key":"XwsbB2KFTI"}],"key":"YTY6QfGHJm"},{"type":"heading","depth":2,"position":{"start":{"line":182,"column":1},"end":{"line":182,"column":1}},"children":[{"type":"text","value":"Example configuration","position":{"start":{"line":182,"column":1},"end":{"line":182,"column":1}},"key":"HnnF0OiF4u"}],"identifier":"example-configuration","label":"Example configuration","html_id":"example-configuration","implicit":true,"key":"BwTNapl2ss"},{"type":"paragraph","position":{"start":{"line":184,"column":1},"end":{"line":188,"column":1}},"children":[{"type":"inlineCode","value":"copperline.example.toml","position":{"start":{"line":184,"column":1},"end":{"line":184,"column":1}},"key":"ogRj4EsOjX"},{"type":"text","value":" in the repository root is a commented reference\ncovering every option -- machine profiles, CPU/FPU, memory,\nchipset, floppy/HDD/CD images, and audio. Copy it to ","position":{"start":{"line":184,"column":1},"end":{"line":184,"column":1}},"key":"yx8zIOVtzS"},{"type":"inlineCode","value":"copperline.toml","position":{"start":{"line":184,"column":1},"end":{"line":184,"column":1}},"key":"WFrTMwpoz1"},{"type":"text","value":"\n(or pass it with ","position":{"start":{"line":184,"column":1},"end":{"line":184,"column":1}},"key":"mhY9e2clB3"},{"type":"inlineCode","value":"--config","position":{"start":{"line":184,"column":1},"end":{"line":184,"column":1}},"key":"uLKD5FDFcf"},{"type":"text","value":") and edit; it doubles as a worked example for\nthe options described in ","position":{"start":{"line":184,"column":1},"end":{"line":184,"column":1}},"key":"g7oJsd4iXw"},{"type":"link","url":"/configuration","position":{"start":{"line":184,"column":1},"end":{"line":184,"column":1}},"children":[{"type":"text","value":"Configuration reference","key":"D7EorRP72w"}],"urlSource":"configuration","dataUrl":"/configuration.json","internal":true,"protocol":"file","key":"fJmQNdDRky"},{"type":"text","value":".","position":{"start":{"line":184,"column":1},"end":{"line":184,"column":1}},"key":"pOY3b1F0rq"}],"key":"fm7Xs5e4ZK"},{"type":"code","lang":"sh","value":"./target/release/copperline --config copperline.example.toml","position":{"start":{"line":190,"column":1},"end":{"line":192,"column":1}},"key":"ZqAgEIoBvM"},{"type":"heading","depth":2,"position":{"start":{"line":194,"column":1},"end":{"line":194,"column":1}},"children":[{"type":"text","value":"Logging","position":{"start":{"line":194,"column":1},"end":{"line":194,"column":1}},"key":"dWgiGbOPBM"}],"identifier":"logging","label":"Logging","html_id":"logging","implicit":true,"key":"TT9ZjWugwq"},{"type":"paragraph","position":{"start":{"line":196,"column":1},"end":{"line":199,"column":1}},"children":[{"type":"text","value":"Copperline logs through the standard Rust ","position":{"start":{"line":196,"column":1},"end":{"line":196,"column":1}},"key":"m9e8QPNXA9"},{"type":"inlineCode","value":"log","position":{"start":{"line":196,"column":1},"end":{"line":196,"column":1}},"key":"TnbyXvTIru"},{"type":"text","value":"/","position":{"start":{"line":196,"column":1},"end":{"line":196,"column":1}},"key":"Jlp52voFX3"},{"type":"inlineCode","value":"env_logger","position":{"start":{"line":196,"column":1},"end":{"line":196,"column":1}},"key":"xQeSVaK0oq"},{"type":"text","value":" machinery.\n","position":{"start":{"line":196,"column":1},"end":{"line":196,"column":1}},"key":"mIK6wg20SE"},{"type":"inlineCode","value":"RUST_LOG=debug","position":{"start":{"line":196,"column":1},"end":{"line":196,"column":1}},"key":"oNKJoqCEC7"},{"type":"text","value":" (or ","position":{"start":{"line":196,"column":1},"end":{"line":196,"column":1}},"key":"Bhx7LmzOo1"},{"type":"inlineCode","value":"trace","position":{"start":{"line":196,"column":1},"end":{"line":196,"column":1}},"key":"va6Nf8534v"},{"type":"text","value":") prints more detail from the CPU and MMIO\nlayers, and is also how the ","position":{"start":{"line":196,"column":1},"end":{"line":196,"column":1}},"key":"OGk6TgKLwE"},{"type":"link","url":"/headless-1","position":{"start":{"line":196,"column":1},"end":{"line":196,"column":1}},"children":[{"type":"text","value":"headless debugger","position":{"start":{"line":196,"column":1},"end":{"line":196,"column":1}},"key":"hd5y5ZiLHO"}],"urlSource":"../debugger/headless","dataUrl":"/headless-1.json","internal":true,"protocol":"file","key":"g1uNYFTl3w"},{"type":"text","value":"\noutput is surfaced.","position":{"start":{"line":196,"column":1},"end":{"line":196,"column":1}},"key":"RRSK6QfYum"}],"key":"rbAbHyCtdE"}],"key":"eRzfZgbpEO"}],"key":"jjUcU8qHfF"},"references":{"cite":{"order":[],"data":{}}},"footer":{"navigation":{"prev":{"title":"Copperline","url":"/","group":"Copperline"},"next":{"title":"Configuration reference","url":"/configuration","group":"User guide"}}},"domain":"http://localhost:3000"}